[
    {
        "key": "group_601abeca11ca4",
        "title": "Hero Image",
        "fields": [
            {
                "key": "field_601abf51cc5c0",
                "label": "Image",
                "name": "image",
                "type": "image",
                "instructions": "",
                "required": 1,
                "conditional_logic": 0,
                "wrapper": {
                    "width": "",
                    "class": "",
                    "id": ""
                },
                "return_format": "array",
                "preview_size": "medium_large",
                "library": "all",
                "min_width": 800,
                "min_height": 100,
                "min_size": "",
                "max_width": "",
                "max_height": "",
                "max_size": 2,
                "mime_types": ""
            },
            {
                "key": "field_601ac075cc5c2",
                "label": "Headline",
                "name": "headline",
                "type": "text",
                "instructions": "",
                "required": 0,
                "conditional_logic": 0,
                "wrapper": {
                    "width": "",
                    "class": "",
                    "id": ""
                },
                "default_value": "",
                "placeholder": "",
                "prepend": "",
                "append": "",
                "maxlength": 99
            },
            {
                "key": "field_601abfb7cc5c1",
                "label": "Excerpt",
                "name": "excerpt",
                "type": "textarea",
                "instructions": "",
                "required": 0,
                "conditional_logic": 0,
                "wrapper": {
                    "width": "",
                    "class": "",
                    "id": ""
                },
                "default_value": "",
                "placeholder": "",
                "maxlength": 320,
                "rows": 4,
                "new_lines": ""
            }
        ],
        "location": [
            [
                {
                    "param": "page",
                    "operator": "==",
                    "value": "8"
                }
            ]
        ],
        "menu_order": 0,
        "position": "acf_after_title",
        "style": "default",
        "label_placement": "top",
        "instruction_placement": "label",
        "hide_on_screen": [
            "discussion",
            "comments",
            "send-trackbacks"
        ],
        "active": true,
        "description": ""
    },
    {
        "key": "group_56200b9d63190",
        "title": "Options",
        "fields": [
            {
                "key": "field_563bbbc0b2982",
                "label": "Google Analytics",
                "name": "",
                "type": "tab",
                "instructions": "",
                "required": 0,
                "conditional_logic": 0,
                "wrapper": {
                    "width": "",
                    "class": "",
                    "id": ""
                },
                "placement": "top",
                "endpoint": 0
            },
            {
                "key": "field_563bbbe4b2983",
                "label": "GA Code",
                "name": "ga_code",
                "type": "text",
                "instructions": "",
                "required": 0,
                "conditional_logic": 0,
                "wrapper": {
                    "width": "",
                    "class": "",
                    "id": ""
                },
                "default_value": "abc",
                "placeholder": "",
                "prepend": "",
                "append": "",
                "maxlength": "",
                "readonly": 0,
                "disabled": 0
            },
            {
                "key": "field_59c95ac61a317",
                "label": "Featured Pages or Posts",
                "name": "",
                "type": "tab",
                "instructions": "",
                "required": 0,
                "conditional_logic": 0,
                "wrapper": {
                    "width": "",
                    "class": "",
                    "id": ""
                },
                "placement": "top",
                "endpoint": 0
            },
            {
                "key": "field_6007065a2b45c",
                "label": "Home Featured Posts",
                "name": "home_featured_posts",
                "type": "repeater",
                "instructions": "",
                "required": 1,
                "conditional_logic": 0,
                "wrapper": {
                    "width": "",
                    "class": "",
                    "id": ""
                },
                "collapsed": "",
                "min": 0,
                "max": 3,
                "layout": "block",
                "button_label": "Add Featured Post",
                "sub_fields": [
                    {
                        "key": "field_6007068b2b45d",
                        "label": "Featured",
                        "name": "post_feature",
                        "type": "post_object",
                        "instructions": "",
                        "required": 1,
                        "conditional_logic": 0,
                        "wrapper": {
                            "width": "",
                            "class": "",
                            "id": ""
                        },
                        "post_type": [
                            "page",
                            "post"
                        ],
                        "taxonomy": "",
                        "allow_null": 0,
                        "multiple": 0,
                        "return_format": "object",
                        "ui": 1
                    },
                    {
                        "key": "field_6007125bd70ab",
                        "label": "Subheadline",
                        "name": "subheadline",
                        "type": "text",
                        "instructions": "",
                        "required": 1,
                        "conditional_logic": 0,
                        "wrapper": {
                            "width": "",
                            "class": "",
                            "id": ""
                        },
                        "default_value": "",
                        "placeholder": "",
                        "prepend": "",
                        "append": "",
                        "maxlength": 120
                    },
                    {
                        "key": "field_6007127bd70ac",
                        "label": "Description",
                        "name": "description",
                        "type": "textarea",
                        "instructions": "",
                        "required": 0,
                        "conditional_logic": 0,
                        "wrapper": {
                            "width": "",
                            "class": "",
                            "id": ""
                        },
                        "default_value": "",
                        "placeholder": "",
                        "maxlength": 240,
                        "rows": 3,
                        "new_lines": ""
                    }
                ]
            }
        ],
        "location": [
            [
                {
                    "param": "options_page",
                    "operator": "==",
                    "value": "options"
                }
            ]
        ],
        "menu_order": 0,
        "position": "normal",
        "style": "default",
        "label_placement": "top",
        "instruction_placement": "label",
        "hide_on_screen": "",
        "active": true,
        "description": ""
    }
]