{
    "key": "group_604fbd81155f2",
    "title": "Quotes",
    "fields": [
        {
            "key": "field_604fbd8ded957",
            "label": "Featured Quote",
            "name": "quote",
            "type": "wysiwyg",
            "instructions": "",
            "required": 1,
            "conditional_logic": 0,
            "wrapper": {
                "width": "",
                "class": "frontpage-quote",
                "id": ""
            },
            "default_value": "",
            "tabs": "text",
            "media_upload": 0,
            "toolbar": "full",
            "delay": 0
        },
        {
            "key": "field_6058f2f8a4a8f",
            "label": "Attribution",
            "name": "attribution_jbc",
            "type": "wysiwyg",
            "instructions": "",
            "required": 0,
            "conditional_logic": 0,
            "wrapper": {
                "width": "",
                "class": "",
                "id": ""
            },
            "default_value": "",
            "tabs": "text",
            "media_upload": 0,
            "toolbar": "full",
            "delay": 0
        }
    ],
    "location": [
        [
            {
                "param": "post_type",
                "operator": "==",
                "value": "quotes"
            }
        ]
    ],
    "menu_order": 0,
    "position": "acf_after_title",
    "style": "default",
    "label_placement": "top",
    "instruction_placement": "label",
    "hide_on_screen": [
        "the_content",
        "revisions",
        "categories",
        "tags"
    ],
    "active": true,
    "description": "",
    "modified": 1623861182
}